---
title: jvm java虚拟机
tags: [interview]
---

jvm代码查看

```
public class JVMTest {
    //常量，静态变量
    private final int i=0;
    private static int k=0;
    //成员变量
    private Object obj=new Object();
    private int sss=1;
    
    //方法体中的局部变量
    public void method1(int i) {
        int j=0;
        int sum=i+j;
        Object scb=obj;
        long start=System.currentTimeMillis();
        method2();
        return;
    }
    public void method2() {
        File file=new File("");
    }
}
```

查看字节码

```
# 定位java类文件位置，运行javap查看字节码命令
javap -c JVMTest > t.txt
```

文档内容

```
Compiled from "JVMTest.java"
public class org.sjq.test.JVMTest {
  static {};
    Code:
       0: iconst_0
       1: putstatic     #16                 // Field k:I
       4: return

  public org.sjq.test.JVMTest();
    Code:
       0: aload_0
       1: invokespecial #21        // Method java/lang/Object."<init>":()V
       4: aload_0
       5: iconst_0
       6: putfield      #23                 // Field i:I
       9: aload_0
      10: new           #3                  // class java/lang/Object
      13: dup
      14: invokespecial #21        // Method java/lang/Object."<init>":()V
      17: putfield      #25                 // Field obj:Ljava/lang/Object;
      20: aload_0
      21: iconst_1
      22: putfield      #27                 // Field sss:I
      25: return

  public void method1(int);
    Code:
       0: iconst_0
       1: istore_2
       2: iload_1
       3: iload_2
       4: iadd
       5: istore_3
       6: aload_0
       7: getfield      #25                 // Field obj:Ljava/lang/Object;
      10: astore        4
      12: invokestatic  #33    // Method java/lang/System.currentTimeMillis:()J
      15: lstore        5
      17: aload_0
      18: invokevirtual #39             // Method method2:()V
      21: return

  public void method2();
    Code:
       0: new           #47                 // class java/io/File
       3: dup
       4: ldc           #49                 // String
       6: invokespecial #51//Method java/io/File."<init>":(Ljava/lang/String;)V
       9: astore_1
      10: return
}

```